sciences/__init__.py
sciences/_version.py
sciences/handlers.py
sciences/tests/__init__.py
sciences/tests/test_handlers.py
sciences-0.0.2.data/data/etc/jupyter/jupyter_notebook_config.d/sciences.json
sciences-0.0.2.data/data/etc/jupyter/jupyter_server_config.d/sciences.json
sciences-0.0.2.data/data/share/jupyter/labextensions/@datalayer/sciences/build_log.json
sciences-0.0.2.data/data/share/jupyter/labextensions/@datalayer/sciences/package.json
sciences-0.0.2.data/data/share/jupyter/labextensions/@datalayer/sciences/schemas/@datalayer/jupyter-aws/package.json.orig
sciences-0.0.2.data/data/share/jupyter/labextensions/@datalayer/sciences/schemas/@datalayer/jupyter-aws/plugin.json
sciences-0.0.2.data/data/share/jupyter/labextensions/@datalayer/sciences/static/design_icons_lib_index_js.e4844025d5c5c76d9788.js
sciences-0.0.2.data/data/share/jupyter/labextensions/@datalayer/sciences/static/design_icons_lib_index_js.e4844025d5c5c76d9788.js.map
sciences-0.0.2.data/data/share/jupyter/labextensions/@datalayer/sciences/static/lib_index_js.a111ccc860e826141a8f.js
sciences-0.0.2.data/data/share/jupyter/labextensions/@datalayer/sciences/static/lib_index_js.a111ccc860e826141a8f.js.map
sciences-0.0.2.data/data/share/jupyter/labextensions/@datalayer/sciences/static/remoteEntry.0dcf9307082c02cc70a4.js
sciences-0.0.2.data/data/share/jupyter/labextensions/@datalayer/sciences/static/remoteEntry.0dcf9307082c02cc70a4.js.map
sciences-0.0.2.data/data/share/jupyter/labextensions/@datalayer/sciences/static/style.js
sciences-0.0.2.data/data/share/jupyter/labextensions/@datalayer/sciences/static/style_index_js.859b9929c33397270eb1.js
sciences-0.0.2.data/data/share/jupyter/labextensions/@datalayer/sciences/static/style_index_js.859b9929c33397270eb1.js.map
sciences-0.0.2.data/data/share/jupyter/labextensions/@datalayer/sciences/static/vendors-node_modules_css-loader_dist_runtime_api_js-node_modules_css-loader_dist_runtime_cssW-72eba1.058d212bf4401555a141.js
sciences-0.0.2.dist-info/METADATA
sciences-0.0.2.dist-info/WHEEL
sciences-0.0.2.dist-info/licenses/LICENSE
sciences-0.0.2.dist-info/RECORD
